LICENSE
MANIFEST.in
README.md
VERSION
setup.cfg
setup.py
sqlalchemy_orm/__init__.py
sqlalchemy_orm/custom_types.py
sqlalchemy_orm/database.py
sqlalchemy_orm/filter.py
sqlalchemy_orm/order_by.py
sqlalchemy_orm/proxy.py
sqlalchemy_orm/query.py
sqlalchemy_orm/session.py
sqlalchemy_orm/typemapper.py
sqlalchemy_orm/utils.py
sqlalchemy_orm.egg-info/PKG-INFO
sqlalchemy_orm.egg-info/SOURCES.txt
sqlalchemy_orm.egg-info/dependency_links.txt
sqlalchemy_orm.egg-info/requires.txt
sqlalchemy_orm.egg-info/top_level.txt
sqlalchemy_orm/base/__init__.py
sqlalchemy_orm/base/base.py
sqlalchemy_orm/base/helper.py
sqlalchemy_orm/base/inheritance.py
sqlalchemy_orm/base/mapper.py
sqlalchemy_orm/patterns/__init__.py
sqlalchemy_orm/patterns/tag.py
sqlalchemy_orm/patterns/tag_mixin.py
sqlalchemy_orm/patterns/taggable.py