Metadata-Version: 2.1
Name: sqlalchemy-orm
Version: 1.2.0
Summary: Data Relation Mapping framework for Python.
Home-page: https://gitlab.com/parob/sqlalchemy-orm
Author: Robert Parker
Author-email: rob@parob.com
License: MIT
Download-URL: https://gitlab.com/parob/sqlalchemy-orm/-/archive/v1.2.0/datarm-v1.2.0.tar.gz
Keywords: SQLAlchemy,ORM
Platform: UNKNOWN
Classifier: Development Status :: 3 - Alpha
Classifier: Intended Audience :: Developers
Classifier: Programming Language :: Python :: 3
Classifier: License :: OSI Approved :: MIT License
Classifier: Operating System :: OS Independent
Provides-Extra: dev
